pythonwhat-russified/State.py
pythonwhat-russified/Test.py
pythonwhat-russified/__init__.py
pythonwhat-russified/converters.py
pythonwhat-russified/feedback.py
pythonwhat-russified/local.py
pythonwhat-russified/parsing.py
pythonwhat-russified/probe.py
pythonwhat-russified/sct_syntax.py
pythonwhat-russified/signatures.py
pythonwhat-russified/tasks.py
pythonwhat-russified/test_exercise.py
pythonwhat-russified/utils.py
pythonwhat-russified/utils_ast.py
pythonwhat-russified/utils_env.py
pythonwhat-russified/checks/__init__.py
pythonwhat-russified/checks/check_funcs.py
pythonwhat-russified/checks/check_function.py
pythonwhat-russified/checks/check_has_context.py
pythonwhat-russified/checks/check_logic.py
pythonwhat-russified/checks/check_object.py
pythonwhat-russified/checks/check_wrappers.py
pythonwhat-russified/checks/has_funcs.py
pythonwhat-russified/test_funcs/__init__.py
pythonwhat-russified/test_funcs/test_compound_statement.py
pythonwhat-russified/test_funcs/test_function.py
pythonwhat-russified/test_funcs/test_object.py
pythonwhat-russified/test_funcs/test_object_accessed.py
pythonwhat-russified/test_funcs/utils.py
pythonwhat_rus/State.py
pythonwhat_rus/Test.py
pythonwhat_rus/__init__.py
pythonwhat_rus/converters.py
pythonwhat_rus/feedback.py
pythonwhat_rus/local.py
pythonwhat_rus/parsing.py
pythonwhat_rus/probe.py
pythonwhat_rus/sct_syntax.py
pythonwhat_rus/signatures.py
pythonwhat_rus/tasks.py
pythonwhat_rus/test_exercise.py
pythonwhat_rus/utils.py
pythonwhat_rus/utils_ast.py
pythonwhat_rus/utils_env.py
pythonwhat_rus/checks/__init__.py
pythonwhat_rus/checks/check_funcs.py
pythonwhat_rus/checks/check_function.py
pythonwhat_rus/checks/check_has_context.py
pythonwhat_rus/checks/check_logic.py
pythonwhat_rus/checks/check_object.py
pythonwhat_rus/checks/check_wrappers.py
pythonwhat_rus/checks/has_funcs.py
pythonwhat_rus/test_funcs/__init__.py
pythonwhat_rus/test_funcs/test_compound_statement.py
pythonwhat_rus/test_funcs/test_function.py
tcs_pythonwhat-2.24.20.dist-info/LICENSE
tcs_pythonwhat-2.24.20.dist-info/METADATA
tcs_pythonwhat-2.24.20.dist-info/WHEEL
tcs_pythonwhat-2.24.20.dist-info/top_level.txt
tcs_pythonwhat-2.24.20.dist-info/RECORD
