Metadata-Version: 2.1
Name: tcs-pythonwhat
Version: 2.24.20
Summary: Submission correctness tests for Python
Home-page: https://github.com/datacamp/pythonwhat
Author: Filip Schouwenaars
Author-email: filip@datacamp.com
Maintainer: Jeroen Hermans
Maintainer-email: content-engineering@datacamp.com
License: UNKNOWN
Platform: UNKNOWN
Classifier: Programming Language :: Python :: 3
Classifier: License :: OSI Approved :: GNU Affero General Public License v3
Classifier: Operating System :: OS Independent
Requires-Dist: asttokens (~=2.0.5)
Requires-Dist: bs4 (~=0.0.1)
Requires-Dist: dill (~=0.3.4)
Requires-Dist: h5py (~=3.1.0)
Requires-Dist: html5lib (~=1.1)
Requires-Dist: jinja2 (~=2.11.3)
Requires-Dist: markdown2 (~=2.3.10)
Requires-Dist: numpy (~=1.19.5)
Requires-Dist: openpyxl (~=3.0.7)
Requires-Dist: pandas (~=1.3.2)
Requires-Dist: pytest-cov (~=2.12.1)
Requires-Dist: pytest (~=6.2.5)
Requires-Dist: requests (~=2.26.0)
Requires-Dist: scipy (~=1.7.1)
Requires-Dist: seaborn (~=0.11.2)
Requires-Dist: sphinx-jinja (~=1.1.1)
Requires-Dist: sphinx-rtd-theme (~=0.5.2)
Requires-Dist: sphinxprettysearchresults (~=0.3.5)
Requires-Dist: sphinx (~=4.1.2)
Requires-Dist: sqlalchemy (~=1.4.23)
Requires-Dist: tcs-protowhat (~=2.1.3)
Requires-Dist: xlrd (~=2.0.1)
